pinax/__init__.py
pinax/badges/__init__.py
pinax/badges/admin.py
pinax/badges/apps.py
pinax/badges/base.py
pinax/badges/models.py
pinax/badges/registry.py
pinax/badges/signals.py
pinax/badges/tasks.py
pinax/badges/urls.py
pinax/badges/views.py
pinax/badges/migrations/0001_initial.py
pinax/badges/migrations/__init__.py
pinax/badges/templatetags/__init__.py
pinax/badges/templatetags/pinax_badges_tags.py
pinax/badges/tests/__init__.py
pinax/badges/tests/models.py
pinax/badges/tests/tests.py
pinax/badges/tests/urls.py
pinax_badges-3.0.0.dist-info/AUTHORS
pinax_badges-3.0.0.dist-info/LICENSE
pinax_badges-3.0.0.dist-info/METADATA
pinax_badges-3.0.0.dist-info/WHEEL
pinax_badges-3.0.0.dist-info/top_level.txt
pinax_badges-3.0.0.dist-info/RECORD
